lyrebird_ios/__init__.py
lyrebird_ios/device_service.py
lyrebird_ios/ios_helper.py
lyrebird_ios/ui.py
lyrebird_ios/config/comparison_table_model.json
lyrebird_ios/config/conf.json
lyrebird_ios/helper/__init__.py
lyrebird_ios/helper/config.py
lyrebird_ios/helper/file_system.py
lyrebird_ios/helper/utils.py
lyrebird_ios/static/vue-resource.js
lyrebird_ios/static/vue-simple-spinner.js
lyrebird_ios/static/vue-simple-spinner.min.js
lyrebird_ios/static/vue.js
lyrebird_ios/static/images/iPhone_default.png
lyrebird_ios/templates/index.html
lyrebird_ios-0.1.6.dist-info/METADATA
lyrebird_ios-0.1.6.dist-info/RECORD
lyrebird_ios-0.1.6.dist-info/WHEEL
lyrebird_ios-0.1.6.dist-info/entry_points.txt
lyrebird_ios-0.1.6.dist-info/top_level.txt
